nexgraphx/__init__.py
nexgraphx/nexgraphx.py
nexgraphx-1.1.4.dist-info/METADATA
nexgraphx-1.1.4.dist-info/WHEEL
nexgraphx-1.1.4.dist-info/top_level.txt
nexgraphx-1.1.4.dist-info/RECORD
