Metadata-Version: 2.1
Name: nexgraphx
Version: 1.1.4
Summary: NexGraphX is a GUI module.
Author: n0dr4w_5 (Dani Adam)
Author-email: <dniadam23@gmail.com>
Keywords: python,gui,graphics
Classifier: Development Status :: 1 - Planning
Classifier: Intended Audience :: Developers
Classifier: Programming Language :: Python :: 3
Classifier: Operating System :: Unix
Classifier: Operating System :: MacOS :: MacOS X
Classifier: Operating System :: Microsoft :: Windows
